hyperledger/__init__.py
hyperledger/client.py
hyperledger/constants.py
hyperledger/errors.py
hyperledger/tls.py
hyperledger/version.py
hyperledger/api/__init__.py
hyperledger/api/block.py
hyperledger/api/blockchain.py
hyperledger/api/chaincode.py
hyperledger/api/network.py
hyperledger/api/registrar.py
hyperledger/api/transaction.py
hyperledger/auth/__init__.py
hyperledger/auth/auth.py
hyperledger/ssladapter/__init__.py
hyperledger/ssladapter/ssl_match_hostname.py
hyperledger/ssladapter/ssladapter.py
hyperledger/utils/__init__.py
hyperledger/utils/decorators.py
hyperledger/utils/types.py
hyperledger/utils/utils.py
hyperledger-0.1.5.dist-info/DESCRIPTION.rst
hyperledger-0.1.5.dist-info/METADATA
hyperledger-0.1.5.dist-info/RECORD
hyperledger-0.1.5.dist-info/WHEEL
hyperledger-0.1.5.dist-info/metadata.json
hyperledger-0.1.5.dist-info/top_level.txt
