Metadata-Version: 1.1
Name: hyperledger
Version: 0.1.5
Summary: Python client for Hyperledger.
Home-page: https://github.com/yeasy/hyperledger-py/
Author: Baohua Yang
Author-email: yangbaohua@gmail.com
License: Apache License v2.0
Keywords: hyperledger,blockchain
Platform: any
Classifier: Development Status :: 3 - Alpha
Classifier: Environment :: Other Environment
Classifier: Intended Audience :: Developers
Classifier: Operating System :: OS Independent
Classifier: Programming Language :: Python
Classifier: Programming Language :: Python :: 2.6
Classifier: Programming Language :: Python :: 2.7
Classifier: Programming Language :: Python :: 3.3
Classifier: Programming Language :: Python :: 3.4
Classifier: Topic :: Utilities
Classifier: License :: OSI Approved :: Apache Software License
